pybench/__init__.py
pybench/__main__.py
pybench/base.py
pybench/generators.py
pybench/helper.py
pybench_2-1.1.0.dist-info/METADATA
pybench_2-1.1.0.dist-info/WHEEL
pybench_2-1.1.0.dist-info/RECORD
